calendar_link/__init__.py
calendar_link/calendar_event.py
calendar_link/calendar_generator.py
calendar_link/exceptions.py
calendar_link/utils.py
calendar_link-0.3.0.dist-info/METADATA
calendar_link-0.3.0.dist-info/WHEEL
calendar_link-0.3.0.dist-info/licenses/LICENSE
calendar_link-0.3.0.dist-info/RECORD
