Metadata-Version: 2.4
Name: calendar-link
Version: 0.3.0
Summary: Generate calendar links and ICS files for Google, Apple, Yahoo, AOL, Microsoft 365, and more
Project-URL: Homepage, https://github.com/nneji123/calendar-link
Project-URL: Repository, https://github.com/nneji123/calendar-link
Project-URL: Issues, https://github.com/nneji123/calendar-link/issues
Author-email: Ifeanyi Nneji <ifeanyinneji777@gmail.com>
License: MIT
License-File: LICENSE
Keywords: apple-calendar,calendar,google-calendar,ics,outlook,yahoo
Classifier: Development Status :: 4 - Beta
Classifier: Intended Audience :: Developers
Classifier: License :: OSI Approved :: MIT License
Classifier: Programming Language :: Python :: 3.11
Classifier: Programming Language :: Python :: 3.12
Classifier: Topic :: Office/Business :: Scheduling
Classifier: Topic :: Software Development :: Libraries :: Python Modules
Requires-Python: >=3.11
Requires-Dist: ical>=11.0.0
Requires-Dist: icalendar>=6.3.2
Requires-Dist: python-dateutil>=2.8.2
Requires-Dist: pytz>=2023.3
Provides-Extra: dev
Requires-Dist: black>=23.0.0; extra == 'dev'
Requires-Dist: flake8>=6.0.0; extra == 'dev'
Requires-Dist: isort>=5.12.0; extra == 'dev'
Requires-Dist: markdown-grid-tables>=0.3.0; extra == 'dev'
Requires-Dist: mdx-include>=1.4.2; extra == 'dev'
Requires-Dist: mkdocs-awesome-pages-plugin>=2.9.0; extra == 'dev'
Requires-Dist: mkdocs-click>=0.8.0; extra == 'dev'
Requires-Dist: mkdocs-git-authors-plugin>=0.3.0; extra == 'dev'
Requires-Dist: mkdocs-git-revision-date-localized-plugin>=1.2.0; extra == 'dev'
Requires-Dist: mkdocs-macros-plugin>=1.0.0; extra == 'dev'
Requires-Dist: mkdocs-material>=9.0.0; extra == 'dev'
Requires-Dist: mkdocs-mermaid2-plugin>=0.6.0; extra == 'dev'
Requires-Dist: mkdocs-minify-plugin>=0.7.0; extra == 'dev'
Requires-Dist: mkdocs-section-index>=0.3.0; extra == 'dev'
Requires-Dist: mkdocs>=1.5.0; extra == 'dev'
Requires-Dist: mypy>=1.0.0; extra == 'dev'
Requires-Dist: pytest-cov>=4.0.0; extra == 'dev'
Requires-Dist: pytest>=7.0.0; extra == 'dev'
